[
    {
        "material": {
            "ambient": [
                0.5,
                0.5,
                0.5
            ],
            "diffuse": [
                0.5,
                0.5,
                0.5
            ],
            "specular": [
                0.5,
                0.5,
                0.5
            ],
            "n": 17,
            "alpha": 0.9,
            "texture": "queen_of_space_space.jpg"
        },
        "vertices": [
            [
                -6.4,
                3.6,
                -400
            ],
            [
                -6.4,
                -3.6,
                -400
            ],
            [
                6.4,
                3.6,
                -400
            ],
            [
                6.4,
                -3.6,
                -400
            ]
        ],
        "normals": [
            [
                0,
                0,
                -400
            ],
            [
                0,
                0,
                -400
            ],
            [
                0,
                0,
                -400
            ],
            [
                0,
                0,
                -400
            ]
        ],
        "uvs": [
            [
                0,
                0
            ],
            [
                0,
                1
            ],
            [
                1,
                1
            ],
            [
                1,
                0
            ]
        ],
        "triangles": [
            [
                0,
                1,
                2
            ],
            [
                1,
                2,
                3
            ]
        ]
    }
   
]
